INSTALL.rst
LICENSE
MANIFEST.in
README.rst
VERSION
requirements.txt
setup.cfg
setup.py
tasks.py
src/bricks/__init__.py
src/bricks/__meta__.py
src/bricks/exceptions.py
src/bricks/forms.py
src/bricks/html5.py
src/bricks/jinja2.py
src/bricks/mixins.py
src/bricks/request.py
src/bricks/types.py
src/bricks/app/__init__.py
src/bricks/app/apps.py
src/bricks/app/models.py
src/bricks/app/urls.py
src/bricks/app/migrations/__init__.py
src/bricks/app/static/js/bricks/actions.js
src/bricks/app/static/js/bricks/commands.js
src/bricks/app/static/js/bricks/core.js
src/bricks/app/static/js/bricks/dialog.js
src/bricks/app/static/js/bricks/django_object.js
src/bricks/app/static/js/bricks/json.js
src/bricks/app/static/js/bricks/util.js
src/bricks/assets/__init__.py
src/bricks/assets/asset.py
src/bricks/assets/assets.py
src/bricks/assets/common.py
src/bricks/assets/manager.py
src/bricks/assets/utils.py
src/bricks/components/__init__.py
src/bricks/components/attrs.py
src/bricks/components/bricks_tags.py
src/bricks/components/children.py
src/bricks/components/core.py
src/bricks/components/css.py
src/bricks/components/data_components.py
src/bricks/components/html5_tags.py
src/bricks/components/text.py
src/bricks/components/ugly.py
src/bricks/components/utils.py
src/bricks/contrib/__init__.py
src/bricks/contrib/bem.py
src/bricks/contrib/bootstrap/__init__.py
src/bricks/contrib/jquery_ui/__init__.py
src/bricks/contrib/mdl/__init__.py
src/bricks/contrib/mdl/components.py
src/bricks/contrib/wagtail/__init__.py
src/bricks/helpers/__init__.py
src/bricks/helpers/attr.py
src/bricks/helpers/escape.py
src/bricks/helpers/extras.py
src/bricks/helpers/hyperlink.py
src/bricks/helpers/render.py
src/bricks/js/__init__.py
src/bricks/js/client.py
src/bricks/json/__init__.py
src/bricks/json/common.py
src/bricks/json/decoders.py
src/bricks/json/encoders.py
src/bricks/json/exceptions.py
src/bricks/json/util.py
src/bricks/ni/__init__.py
src/bricks/ni/converter.py
src/bricks/ni/to_ast.py
src/django_bricks.egg-info/PKG-INFO
src/django_bricks.egg-info/SOURCES.txt
src/django_bricks.egg-info/dependency_links.txt
src/django_bricks.egg-info/not-zip-safe
src/django_bricks.egg-info/requires.txt
src/django_bricks.egg-info/top_level.txt